pyplan/__init__.py
pyplan/__main__.py
pyplan/pyplan_ide.py
pyplan/config/__init__.py
pyplan/config/urls.py
pyplan/config/wsgi.py
pyplan/config/settings/__init__.py
pyplan/config/settings/common.py
pyplan/config/settings/desktop.py
pyplan/config/settings/local.py
pyplan/config/settings/production.py
pyplan/demos/home.json
pyplan/demos/Examples/01-Visualization/01-California Power Plants/California Power Plants.png
pyplan/demos/Examples/01-Visualization/01-California Power Plants/California Power Plants.ppl
pyplan/demos/Examples/01-Visualization/01-California Power Plants/Data/California_Power_Plant.csv
pyplan/demos/Examples/01-Visualization/02-Visualization Libraries in Pyplan/Visualization Libraries in Pyplan.ppl
pyplan/demos/Examples/01-Visualization/03-Gapminder Data Analysis/Gapminder Data Analysis.png
pyplan/demos/Examples/01-Visualization/03-Gapminder Data Analysis/Gapminder Data Analysis.ppl
pyplan/demos/Examples/01-Visualization/03-Gapminder Data Analysis/gapminder_data.csv
pyplan/demos/Examples/02-Machine Learning/01-Supplier route optimization/Supplier route optimization.ppl
pyplan/demos/Examples/02-Machine Learning/01-Supplier route optimization/Files/DemoQuilmesDB.db
pyplan/demos/Examples/02-Machine Learning/01-Supplier route optimization/Files/gba_clientes.csv
pyplan/demos/Examples/02-Machine Learning/01-Supplier route optimization/Files/sale.csv
pyplan/demos/Examples/02-Machine Learning/01-Supplier route optimization/Files/testClasif.pkl
pyplan/demos/Examples/02-Machine Learning/02-Iris Sample/Iris Sample.png
pyplan/demos/Examples/02-Machine Learning/02-Iris Sample/Iris Sample.ppl
pyplan/demos/Examples/02-Machine Learning/02-Iris Sample/trained_model.sav
pyplan/demos/Examples/03-Regressions/Regressions.png
pyplan/demos/Examples/03-Regressions/Regressions.ppl
pyplan/demos/Examples/04-Stochastic models/04-Stochastic models (Market Model).ppl
pyplan/demos/Examples/05-Pyplan Library/01-Basic concepts/Basic concepts.png
pyplan_ide-0.31.37.dist-info/LICENSE
pyplan_ide-0.31.37.dist-info/METADATA
pyplan_ide-0.31.37.dist-info/WHEEL
pyplan_ide-0.31.37.dist-info/entry_points.txt
pyplan_ide-0.31.37.dist-info/top_level.txt
pyplan_ide-0.31.37.dist-info/RECORD
