Metadata-Version: 2.1
Name: pyplan-ide
Version: 0.31.37
Summary: Pyplan is a graphical Integrated Development Environment for creating and sharing Data Analytics Apps.
Home-page: https://github.com/pyplan/pyplan-ide
Author: Pyplan
Author-email: info@pyplan.com
License: MIT
Platform: UNKNOWN
Classifier: Environment :: Web Environment
Classifier: Intended Audience :: Developers
Classifier: Intended Audience :: End Users/Desktop
Classifier: Intended Audience :: Financial and Insurance Industry
Classifier: Operating System :: OS Independent
Classifier: License :: OSI Approved :: MIT License
Classifier: Programming Language :: Python
Classifier: Programming Language :: Python :: 3.7
Classifier: Topic :: Software Development
Classifier: Topic :: Scientific/Engineering
Classifier: Topic :: Scientific/Engineering :: Visualization
Requires-Dist: Django (==2.2.13)
Requires-Dist: django-configurations (==2.2)
Requires-Dist: pyplan-core (>=0.1.22)
Requires-Dist: channels (==2.4.0)
Requires-Dist: django-model-utils (==4.0.0)
Requires-Dist: jsonfield (==2.0.2)
Requires-Dist: websocket-client (==0.57.0)
Requires-Dist: djangorestframework (==3.10.2)
Requires-Dist: django-filter (==2.3.0)
Requires-Dist: coreapi
Requires-Dist: django-cors-headers
Requires-Dist: django-environ (==0.4.5)
Requires-Dist: requests (==2.22.0)
Requires-Dist: user-agents (>=2.0)
Requires-Dist: ipython (==7.8.0)
Requires-Dist: autopep8 (>=1.4.4)
Requires-Dist: django-nose (==1.4.6)
Requires-Dist: openpyxl (==2.6.2)
Requires-Dist: xlrd (==1.2.0)
Requires-Dist: jsonpickle (==1.2)
Requires-Dist: folium (==0.10.1)
Requires-Dist: scikit-learn (==0.22)
Requires-Dist: statsmodels (==0.11.0)
Requires-Dist: whitenoise (>=4.1.4)
Requires-Dist: toolz (==0.10.0)
Requires-Dist: plotly (==4.4.1)
Requires-Dist: bokeh (==1.3.4)
Requires-Dist: matplotlib (==3.1.2)
Requires-Dist: sqlalchemy (==1.3.13)
